{"wYMjThlfJCzKKjypOxC2dg==":"wp_20160920_14_33_36_rich-2000x1127.jpg","f391QiYnf7tLJZSZex/Pcw==":"img-2000x1124.jpg","yqjqDE0EE+3a8sN8wglLvA==":"img-2000x1331.jpg","1KLKlbHN36vuysI7UFqX/g==":"img-2000x1125.jpg","LnW5P43Lam1VJYxI25sKzw==":"img-1-2000x1124.jpg","KhaQOANUX6TCksF/ncZ0Ow==":"img_2320_compressed-2000x1331.jpg","NIlUn2P/tBL2+EJFdIlgtw==":"logo_favicon-128x128.jpg","h7blSQ5kJPQYeDzMDgc6AA==":"logo_travel-gorizont2-420x128.png","mXe/KbKZ+a//MtnnSvG5Fw==":"untitled-1-1%20transp-small-416x128.png","Cr01y7oruAmZhed6o9wdPg==":"logo_travel%20shelet%20invert%20png-495x128.png","6t7gyQnoIs/X1vSj+MNhew==":"logo_travel%20shelet%20invert%20png-495x128.png","Bgg5M2erOxnoavxkbfhqtA==":"backup_of_logo_travel2-2-128x128.png","GcT/a1kp1KZzDv3lcA6jMQ==":"logo_travel_200x200-128x128.png","9rf3bTRldcV0Q3DW3qGY/A==":"img-1-2000x1125.jpg","jR4q4Nj8H6WufgNdmyaopg==":"img_20141126-2000x1125.jpg","WP6G2MJ68Xy19J7v+11tbg==":"p1100434-2000x1125.jpg","ZaSPOsEKKrb/MTwZVqFRyQ==":"logo_travel%20invert%20kvadrat%202-2_compressed-265x265.jpg","Ahvi82nb5sifns7POpSi7A==":"backup_of_logo_travel2-2-265x265.png","g53A6mLIeppnL/XstuwaKA==":"mbr-1400x933.jpg"}